skill_plotter/__init__.py
skill_plotter/main.py
skill_plotter/plotter.py
skill_plotter/preparator.py
skill_plotter/utils.py
skill_plotter-0.4.2.dist-info/LICENSE
skill_plotter-0.4.2.dist-info/METADATA
skill_plotter-0.4.2.dist-info/WHEEL
skill_plotter-0.4.2.dist-info/entry_points.txt
skill_plotter-0.4.2.dist-info/RECORD
