Metadata-Version: 2.1
Name: skill-plotter
Version: 0.4.2
Summary: CLI tool to generate a plot of your skills
Home-page: https://skillplotter.readthedocs.io/
License: MIT
Keywords: skill,plot,cli,tool,cv,resume
Author: Andre Wohnsland
Author-email: 50302161+AndreWohnsland@users.noreply.github.com
Requires-Python: >=3.10,<3.13
Classifier: License :: OSI Approved :: MIT License
Classifier: Programming Language :: Python :: 3
Classifier: Programming Language :: Python :: 3.10
Classifier: Programming Language :: Python :: 3.11
Requires-Dist: jsonschema (>=4.23.0,<5.0.0)
Requires-Dist: matplotlib (>=3.10.1,<4.0.0)
Requires-Dist: pandas (>=2.2.3,<3.0.0)
Requires-Dist: typer[all] (>=0.15.2,<0.16.0)
Project-URL: Documentation, https://skillplotter.readthedocs.io
Project-URL: Repository, https://github.com/AndreWohnsland/skillplotter
